google/cloud/gkeconnect/gateway/__init__.py
google/cloud/gkeconnect/gateway/gapic_version.py
google/cloud/gkeconnect/gateway/py.typed
google/cloud/gkeconnect/gateway_v1/__init__.py
google/cloud/gkeconnect/gateway_v1/gapic_metadata.json
google/cloud/gkeconnect/gateway_v1/gapic_version.py
google/cloud/gkeconnect/gateway_v1/py.typed
google/cloud/gkeconnect/gateway_v1/services/__init__.py
google/cloud/gkeconnect/gateway_v1/services/gateway_control/__init__.py
google/cloud/gkeconnect/gateway_v1/services/gateway_control/client.py
google/cloud/gkeconnect/gateway_v1/services/gateway_control/transports/__init__.py
google/cloud/gkeconnect/gateway_v1/services/gateway_control/transports/base.py
google/cloud/gkeconnect/gateway_v1/services/gateway_control/transports/rest.py
google/cloud/gkeconnect/gateway_v1/services/gateway_control/transports/rest_base.py
google/cloud/gkeconnect/gateway_v1/types/__init__.py
google/cloud/gkeconnect/gateway_v1/types/control.py
google/cloud/gkeconnect/gateway_v1beta1/__init__.py
google/cloud/gkeconnect/gateway_v1beta1/gapic_metadata.json
google/cloud/gkeconnect/gateway_v1beta1/gapic_version.py
google/cloud/gkeconnect/gateway_v1beta1/py.typed
google/cloud/gkeconnect/gateway_v1beta1/services/__init__.py
google/cloud/gkeconnect/gateway_v1beta1/services/gateway_control/__init__.py
google/cloud/gkeconnect/gateway_v1beta1/services/gateway_control/client.py
google/cloud/gkeconnect/gateway_v1beta1/services/gateway_control/transports/__init__.py
google/cloud/gkeconnect/gateway_v1beta1/services/gateway_control/transports/base.py
google/cloud/gkeconnect/gateway_v1beta1/services/gateway_control/transports/rest.py
google/cloud/gkeconnect/gateway_v1beta1/services/gateway_control/transports/rest_base.py
google/cloud/gkeconnect/gateway_v1beta1/types/__init__.py
google/cloud/gkeconnect/gateway_v1beta1/types/control.py
google_cloud_gke_connect_gateway-0.11.0.dist-info/licenses/LICENSE
google_cloud_gke_connect_gateway-0.11.0.dist-info/METADATA
google_cloud_gke_connect_gateway-0.11.0.dist-info/WHEEL
google_cloud_gke_connect_gateway-0.11.0.dist-info/top_level.txt
google_cloud_gke_connect_gateway-0.11.0.dist-info/RECORD
